python_package/__init__.py
python_package/dman.py
python_package/hello_world.py
python_package/holomap_ex.py
python_package/holoviz_ex.py
python_package/mortgage_simulator/__init__,py
python_package/mortgage_simulator/mortgage_sim.py
python_package/mortgage_simulator/mortgage_sim_holo.py
mortgage_simulator-0.0.2.dist-info/LICENSE
mortgage_simulator-0.0.2.dist-info/WHEEL
mortgage_simulator-0.0.2.dist-info/METADATA
mortgage_simulator-0.0.2.dist-info/RECORD
